i8c/__init__.py
i8c/archspec.py
i8c/cmdline.py
i8c/compat.py
i8c/constants.py
i8c/compiler/__init__.py
i8c/compiler/blocks.py
i8c/compiler/commands.py
i8c/compiler/driver.py
i8c/compiler/emitter.py
i8c/compiler/exceptions.py
i8c/compiler/externals.py
i8c/compiler/lexer.py
i8c/compiler/logger.py
i8c/compiler/names.py
i8c/compiler/operations.py
i8c/compiler/optimizer.py
i8c/compiler/parser.py
i8c/compiler/serializer.py
i8c/compiler/stack.py
i8c/compiler/target.py
i8c/compiler/types.py
i8c/compiler/visitors.py
i8c/runtime/__init__.py
i8c/runtime/context.py
i8c/runtime/core.py
i8c/runtime/coverage.py
i8c/runtime/driver.py
i8c/runtime/exceptions.py
i8c/runtime/libi8xctx.py
i8c/runtime/memory.py
i8c/runtime/provider.py
i8c/runtime/testcase.py
i8c/runtime/pythonctx/__init__.py
i8c/runtime/pythonctx/functions.py
i8c/runtime/pythonctx/leb128.py
i8c/runtime/pythonctx/operations.py
i8c/runtime/pythonctx/stack.py
i8c/runtime/pythonctx/types.py
i8c-0.0.6.dist-info/DESCRIPTION.rst
i8c-0.0.6.dist-info/METADATA
i8c-0.0.6.dist-info/RECORD
i8c-0.0.6.dist-info/WHEEL
i8c-0.0.6.dist-info/entry_points.txt
i8c-0.0.6.dist-info/metadata.json
i8c-0.0.6.dist-info/top_level.txt
