Metadata-Version: 2.0
Name: i8c
Version: 0.0.6
Summary: Infinity Note Compiler
Home-page: https://infinitynotes.org/
Author: Gary Benson
Author-email: infinity@sourceware.org
License: GPLv3+ and LGPLv2.1+
Platform: UNKNOWN
Classifier: Development Status :: 4 - Beta
Classifier: Environment :: Console
Classifier: Intended Audience :: Developers
Classifier: License :: OSI Approved :: GNU General Public License v3 or later (GPLv3+)
Classifier: License :: OSI Approved :: GNU Lesser General Public License v2 or later (LGPLv2+)
Classifier: Operating System :: OS Independent
Classifier: Topic :: Software Development :: Compilers
Classifier: Programming Language :: Python :: 2
Classifier: Programming Language :: Python :: 2.7
Classifier: Programming Language :: Python :: 3
Classifier: Programming Language :: Python :: 3.3
Classifier: Programming Language :: Python :: 3.4
Classifier: Programming Language :: Python :: 3.5
Classifier: Programming Language :: Python :: 3.6
Requires-Dist: arpy
Requires-Dist: pyelftools (>=0.24)
